{"data":{"site":{"pathPrefix":"/open-checkbook"},"postgres":{"vendor":[{"vendorName":"TRANSDEV SERVICES INC","vendorAddress":"Lombard, IL, 60148, US","vendorNumber":"99744","passThroughPayee":false,"payments":[{"checkNumber":"230279","checkDate":"2019-04-04T00:00:00","checkAmount":"14335.20","statusCode":"CLEARED","vendorName":"TRANSDEV SERVICES INC","invoicePaymentDistAmount":14335.2,"fundDesc":"Transportation Grants Fund","agencyDesc":"Department of Transportation","agencyByAgencyCodeMasked":{"deptName":"Department of Transportation","deptSlug":"transportation","totalAmount":73651984.0099998},"appropDesc":"FY07 Sec 5316 MI 37 X035","costcenterDesc":"Job Access _ Mobility Management_207019","objectDesc":"Contract Svcs-Other-Misc","objectDescShorthand":"Professional and Contractual Services","vendorType":"SUPPLIER","partyType":"ORGANIZATION"},{"checkNumber":"229310","checkDate":"2019-03-14T00:00:00","checkAmount":"681827.77","statusCode":"CLEARED","vendorName":"TRANSDEV SERVICES INC","invoicePaymentDistAmount":681827.77,"fundDesc":"Transportation Operation","agencyDesc":"Department of Transportation","agencyByAgencyCodeMasked":{"deptName":"Department of Transportation","deptSlug":"transportation","totalAmount":73651984.0099998},"appropDesc":"DDOT Transportation","costcenterDesc":"DOT ADA Transportation Services","objectDesc":"Contract Svcs-Other-Misc","objectDescShorthand":"Professional and Contractual Services","vendorType":"SUPPLIER","partyType":"ORGANIZATION"},{"checkNumber":"227754","checkDate":"2019-02-14T00:00:00","checkAmount":"678740.16","statusCode":"CLEARED","vendorName":"TRANSDEV SERVICES INC","invoicePaymentDistAmount":678740.16,"fundDesc":"Transportation Operation","agencyDesc":"Department of Transportation","agencyByAgencyCodeMasked":{"deptName":"Department of Transportation","deptSlug":"transportation","totalAmount":73651984.0099998},"appropDesc":"DDOT Transportation","costcenterDesc":"DOT ADA Transportation Services","objectDesc":"Contract Svcs-Other-Misc","objectDescShorthand":"Professional and Contractual Services","vendorType":"SUPPLIER","partyType":"ORGANIZATION"},{"checkNumber":"227355","checkDate":"2019-01-31T00:00:00","checkAmount":"15661.80","statusCode":"CLEARED","vendorName":"TRANSDEV SERVICES INC","invoicePaymentDistAmount":15661.8,"fundDesc":"Transportation Grants Fund","agencyDesc":"Department of Transportation","agencyByAgencyCodeMasked":{"deptName":"Department of Transportation","deptSlug":"transportation","totalAmount":73651984.0099998},"appropDesc":"FY07 Sec 5316 MI 37 X035","costcenterDesc":"Job Access _ Mobility Management_207019","objectDesc":"Contract Svcs-Other-Misc","objectDescShorthand":"Professional and Contractual Services","vendorType":"SUPPLIER","partyType":"ORGANIZATION"},{"checkNumber":"226829","checkDate":"2019-01-17T00:00:00","checkAmount":"707004.23","statusCode":"NEGOTIABLE","vendorName":"TRANSDEV SERVICES INC","invoicePaymentDistAmount":707004.23,"fundDesc":"Transportation Operation","agencyDesc":"Department of Transportation","agencyByAgencyCodeMasked":{"deptName":"Department of Transportation","deptSlug":"transportation","totalAmount":73651984.0099998},"appropDesc":"DDOT Transportation","costcenterDesc":"DOT ADA Transportation Services","objectDesc":"Contract Svcs-Other-Misc","objectDescShorthand":"Professional and Contractual Services","vendorType":"SUPPLIER","partyType":"ORGANIZATION"},{"checkNumber":"226404","checkDate":"2019-01-10T00:00:00","checkAmount":"737143.21","statusCode":"NEGOTIABLE","vendorName":"TRANSDEV SERVICES INC","invoicePaymentDistAmount":17829.9,"fundDesc":"Transportation Grants Fund","agencyDesc":"Department of Transportation","agencyByAgencyCodeMasked":{"deptName":"Department of Transportation","deptSlug":"transportation","totalAmount":73651984.0099998},"appropDesc":"FY07 Sec 5316 MI 37 X035","costcenterDesc":"Job Access _ Mobility Management_207019","objectDesc":"Contract Svcs-Other-Misc","objectDescShorthand":"Professional and Contractual Services","vendorType":"SUPPLIER","partyType":"ORGANIZATION"},{"checkNumber":"226404","checkDate":"2019-01-10T00:00:00","checkAmount":"737143.21","statusCode":"NEGOTIABLE","vendorName":"TRANSDEV SERVICES INC","invoicePaymentDistAmount":719313.31,"fundDesc":"Transportation Operation","agencyDesc":"Department of Transportation","agencyByAgencyCodeMasked":{"deptName":"Department of Transportation","deptSlug":"transportation","totalAmount":73651984.0099998},"appropDesc":"DDOT Transportation","costcenterDesc":"DOT ADA Transportation Services","objectDesc":"Contract Svcs-Other-Misc","objectDescShorthand":"Professional and Contractual Services","vendorType":"SUPPLIER","partyType":"ORGANIZATION"},{"checkNumber":"226158","checkDate":"2018-12-20T00:00:00","checkAmount":"1555583.83","statusCode":"NEGOTIABLE","vendorName":"TRANSDEV SERVICES INC","invoicePaymentDistAmount":789587.25,"fundDesc":"Transportation Operation","agencyDesc":"Department of Transportation","agencyByAgencyCodeMasked":{"deptName":"Department of Transportation","deptSlug":"transportation","totalAmount":73651984.0099998},"appropDesc":"DDOT Transportation","costcenterDesc":"DOT ADA Transportation Services","objectDesc":"Contract Svcs-Other-Misc","objectDescShorthand":"Professional and Contractual Services","vendorType":"SUPPLIER","partyType":"ORGANIZATION"},{"checkNumber":"226158","checkDate":"2018-12-20T00:00:00","checkAmount":"1555583.83","statusCode":"NEGOTIABLE","vendorName":"TRANSDEV SERVICES INC","invoicePaymentDistAmount":765996.58,"fundDesc":"Transportation Operation","agencyDesc":"Department of Transportation","agencyByAgencyCodeMasked":{"deptName":"Department of Transportation","deptSlug":"transportation","totalAmount":73651984.0099998},"appropDesc":"DDOT Transportation","costcenterDesc":"DOT ADA Transportation Services","objectDesc":"Contract Svcs-Other-Misc","objectDescShorthand":"Professional and Contractual Services","vendorType":"SUPPLIER","partyType":"ORGANIZATION"},{"checkNumber":"225659","checkDate":"2018-12-13T00:00:00","checkAmount":"19300.05","statusCode":"NEGOTIABLE","vendorName":"TRANSDEV SERVICES INC","invoicePaymentDistAmount":19300.05,"fundDesc":"Transportation Grants Fund","agencyDesc":"Department of Transportation","agencyByAgencyCodeMasked":{"deptName":"Department of Transportation","deptSlug":"transportation","totalAmount":73651984.0099998},"appropDesc":"FY07 Sec 5316 MI 37 X035","costcenterDesc":"Job Access _ Mobility Management_207019","objectDesc":"Contract Svcs-Other-Misc","objectDescShorthand":"Professional and Contractual Services","vendorType":"SUPPLIER","partyType":"ORGANIZATION"},{"checkNumber":"224897","checkDate":"2018-11-29T00:00:00","checkAmount":"17196.30","statusCode":"NEGOTIABLE","vendorName":"TRANSDEV SERVICES INC","invoicePaymentDistAmount":17196.3,"fundDesc":"Transportation Grants Fund","agencyDesc":"Department of Transportation","agencyByAgencyCodeMasked":{"deptName":"Department of Transportation","deptSlug":"transportation","totalAmount":73651984.0099998},"appropDesc":"FY07 Sec 5316 MI 37 X035","costcenterDesc":"Job Access _ Mobility Management_207019","objectDesc":"Contract Svcs-Other-Misc","objectDescShorthand":"Professional and Contractual Services","vendorType":"SUPPLIER","partyType":"ORGANIZATION"},{"checkNumber":"224259","checkDate":"2018-11-15T00:00:00","checkAmount":"15929.10","statusCode":"NEGOTIABLE","vendorName":"TRANSDEV SERVICES INC","invoicePaymentDistAmount":15929.1,"fundDesc":"Transportation Grants Fund","agencyDesc":"Department of Transportation","agencyByAgencyCodeMasked":{"deptName":"Department of Transportation","deptSlug":"transportation","totalAmount":73651984.0099998},"appropDesc":"FY07 Sec 5316 MI 37 X035","costcenterDesc":"Job Access _ Mobility Management_207019","objectDesc":"Contract Svcs-Other-Misc","objectDescShorthand":"Professional and Contractual Services","vendorType":"SUPPLIER","partyType":"ORGANIZATION"},{"checkNumber":"221752","checkDate":"2018-09-06T00:00:00","checkAmount":"718183.07","statusCode":"CLEARED","vendorName":"TRANSDEV SERVICES INC","invoicePaymentDistAmount":718183.07,"fundDesc":"Transportation Operation","agencyDesc":"Department of Transportation","agencyByAgencyCodeMasked":{"deptName":"Department of Transportation","deptSlug":"transportation","totalAmount":73651984.0099998},"appropDesc":"DDOT Transportation","costcenterDesc":"DOT ADA Transportation Services","objectDesc":"Contract Svcs-Other-Misc","objectDescShorthand":"Professional and Contractual Services","vendorType":"SUPPLIER","partyType":"ORGANIZATION"},{"checkNumber":"221496","checkDate":"2018-08-30T00:00:00","checkAmount":"14468.85","statusCode":"NEGOTIABLE","vendorName":"TRANSDEV SERVICES INC","invoicePaymentDistAmount":14468.85,"fundDesc":"Transportation Grants Fund","agencyDesc":"Department of Transportation","agencyByAgencyCodeMasked":{"deptName":"Department of Transportation","deptSlug":"transportation","totalAmount":73651984.0099998},"appropDesc":"FY07 Sec 5316 MI 37 X035","costcenterDesc":"Job Access _ Mobility Management_207019","objectDesc":"Contract Svcs-Other-Misc","objectDescShorthand":"Professional and Contractual Services","vendorType":"SUPPLIER","partyType":"ORGANIZATION"},{"checkNumber":"220665","checkDate":"2018-08-09T00:00:00","checkAmount":"723769.18","statusCode":"CLEARED","vendorName":"TRANSDEV SERVICES INC","invoicePaymentDistAmount":708854.83,"fundDesc":"Transportation Operation","agencyDesc":"Department of Transportation","agencyByAgencyCodeMasked":{"deptName":"Department of Transportation","deptSlug":"transportation","totalAmount":73651984.0099998},"appropDesc":"DDOT Transportation","costcenterDesc":"DOT ADA Transportation Services","objectDesc":"Contract Svcs-Other-Misc","objectDescShorthand":"Professional and Contractual Services","vendorType":"SUPPLIER","partyType":"ORGANIZATION"},{"checkNumber":"220665","checkDate":"2018-08-09T00:00:00","checkAmount":"723769.18","statusCode":"CLEARED","vendorName":"TRANSDEV SERVICES INC","invoicePaymentDistAmount":14914.35,"fundDesc":"Transportation Grants Fund","agencyDesc":"Department of Transportation","agencyByAgencyCodeMasked":{"deptName":"Department of Transportation","deptSlug":"transportation","totalAmount":73651984.0099998},"appropDesc":"FY07 Sec 5316 MI 37 X035","costcenterDesc":"Job Access _ Mobility Management_207019","objectDesc":"Contract Svcs-Other-Misc","objectDescShorthand":"Professional and Contractual Services","vendorType":"SUPPLIER","partyType":"ORGANIZATION"},{"checkNumber":"219315","checkDate":"2018-07-05T00:00:00","checkAmount":"752908.21","statusCode":"CLEARED","vendorName":"TRANSDEV SERVICES INC","invoicePaymentDistAmount":14795.55,"fundDesc":"Transportation Grants Fund","agencyDesc":"Department of Transportation","agencyByAgencyCodeMasked":{"deptName":"Department of Transportation","deptSlug":"transportation","totalAmount":73651984.0099998},"appropDesc":"FY07 Sec 5316 MI 37 X035","costcenterDesc":"Job Access _ Mobility Management_207019","objectDesc":"Contract Svcs-Other-Misc","objectDescShorthand":"Professional and Contractual Services","vendorType":"SUPPLIER","partyType":"ORGANIZATION"},{"checkNumber":"219315","checkDate":"2018-07-05T00:00:00","checkAmount":"752908.21","statusCode":"CLEARED","vendorName":"TRANSDEV SERVICES INC","invoicePaymentDistAmount":738112.66,"fundDesc":"Transportation Operation","agencyDesc":"Department of Transportation","agencyByAgencyCodeMasked":{"deptName":"Department of Transportation","deptSlug":"transportation","totalAmount":73651984.0099998},"appropDesc":"DDOT Transportation","costcenterDesc":"DOT ADA Transportation Services","objectDesc":"Contract Svcs-Other-Misc","objectDescShorthand":"Professional and Contractual Services","vendorType":"SUPPLIER","partyType":"ORGANIZATION"},{"checkNumber":"233403","checkDate":"2019-06-06T00:00:00","checkAmount":"802708.32","statusCode":"CLEARED","vendorName":"TRANSDEV SERVICES INC","invoicePaymentDistAmount":15568.9,"fundDesc":"Transportation Grants Fund","agencyDesc":"Department of Transportation","agencyByAgencyCodeMasked":{"deptName":"Department of Transportation","deptSlug":"transportation","totalAmount":73651984.0099998},"appropDesc":"FY07 Sec 5316 MI 37 X035","costcenterDesc":"Job Access _ Mobility Management_207019","objectDesc":"Contract Svcs-Other-Misc","objectDescShorthand":"Professional and Contractual Services","vendorType":"SUPPLIER","partyType":"ORGANIZATION"},{"checkNumber":"233403","checkDate":"2019-06-06T00:00:00","checkAmount":"802708.32","statusCode":"CLEARED","vendorName":"TRANSDEV SERVICES INC","invoicePaymentDistAmount":444.35,"fundDesc":"Transportation Grants Fund","agencyDesc":"Department of Transportation","agencyByAgencyCodeMasked":{"deptName":"Department of Transportation","deptSlug":"transportation","totalAmount":73651984.0099998},"appropDesc":"FY07 Sec 5317 MI 57 X013","costcenterDesc":"New Freedom _ Buy Vans for Expansion_207033","objectDesc":"Contract Svcs-Other-Misc","objectDescShorthand":"Professional and Contractual Services","vendorType":"SUPPLIER","partyType":"ORGANIZATION"},{"checkNumber":"233403","checkDate":"2019-06-06T00:00:00","checkAmount":"802708.32","statusCode":"CLEARED","vendorName":"TRANSDEV SERVICES INC","invoicePaymentDistAmount":786695.07,"fundDesc":"Transportation Operation","agencyDesc":"Department of Transportation","agencyByAgencyCodeMasked":{"deptName":"Department of Transportation","deptSlug":"transportation","totalAmount":73651984.0099998},"appropDesc":"DDOT Transportation","costcenterDesc":"DOT ADA Transportation Services","objectDesc":"Contract Svcs-Other-Misc","objectDescShorthand":"Professional and Contractual Services","vendorType":"SUPPLIER","partyType":"ORGANIZATION"},{"checkNumber":"231928","checkDate":"2019-05-09T00:00:00","checkAmount":"16785.45","statusCode":"NEGOTIABLE","vendorName":"TRANSDEV SERVICES INC","invoicePaymentDistAmount":16785.45,"fundDesc":"Transportation Grants Fund","agencyDesc":"Department of Transportation","agencyByAgencyCodeMasked":{"deptName":"Department of Transportation","deptSlug":"transportation","totalAmount":73651984.0099998},"appropDesc":"FY07 Sec 5317 MI 57 X013","costcenterDesc":"New Freedom _ Buy Vans for Expansion_207033","objectDesc":"Contract Svcs-Other-Misc","objectDescShorthand":"Professional and Contractual Services","vendorType":"SUPPLIER","partyType":"ORGANIZATION"},{"checkNumber":"231785","checkDate":"2019-05-02T00:00:00","checkAmount":"703465.75","statusCode":"NEGOTIABLE","vendorName":"TRANSDEV SERVICES INC","invoicePaymentDistAmount":16280.55,"fundDesc":"Transportation Grants Fund","agencyDesc":"Department of Transportation","agencyByAgencyCodeMasked":{"deptName":"Department of Transportation","deptSlug":"transportation","totalAmount":73651984.0099998},"appropDesc":"FY07 Sec 5317 MI 57 X013","costcenterDesc":"New Freedom _ Buy Vans for Expansion_207033","objectDesc":"Contract Svcs-Other-Misc","objectDescShorthand":"Professional and Contractual Services","vendorType":"SUPPLIER","partyType":"ORGANIZATION"},{"checkNumber":"231785","checkDate":"2019-05-02T00:00:00","checkAmount":"703465.75","statusCode":"NEGOTIABLE","vendorName":"TRANSDEV SERVICES INC","invoicePaymentDistAmount":687185.2,"fundDesc":"Transportation Operation","agencyDesc":"Department of Transportation","agencyByAgencyCodeMasked":{"deptName":"Department of Transportation","deptSlug":"transportation","totalAmount":73651984.0099998},"appropDesc":"DDOT Transportation","costcenterDesc":"DOT ADA Transportation Services","objectDesc":"Contract Svcs-Other-Misc","objectDescShorthand":"Professional and Contractual Services","vendorType":"SUPPLIER","partyType":"ORGANIZATION"}]}]}},"pageContext":{"isCreatedByStatefulCreatePages":false,"number":"99744"}}