{"data":{"site":{"pathPrefix":"/open-checkbook"},"postgres":{"vendor":[{"vendorName":"INCOME TAX INVESTIGATORS ASSOC","vendorAddress":"DETROIT, MI, 48226, US","vendorNumber":"97749","passThroughPayee":true,"payments":[{"checkNumber":"2082725","checkDate":"2018-09-24T00:00:00","checkAmount":"20.00","statusCode":"CLEARED","vendorName":"INCOME TAX INVESTIGATORS ASSOC","invoicePaymentDistAmount":20,"fundDesc":"General Fund","agencyDesc":"Pass Through Payments","agencyByAgencyCodeMasked":{"deptName":"Pass Through Payments","deptSlug":"pass-throughs","totalAmount":451128009.3},"appropDesc":"Undefined Appropriations","costcenterDesc":"Default Cost Center","objectDesc":"Empl W/H-Other Deductions","objectDescShorthand":"Pass Through","vendorType":"ADVANCE PAY","partyType":"ORGANIZATION"},{"checkNumber":"3454579","checkDate":"2019-01-10T00:00:00","checkAmount":"50.00","statusCode":"CLEARED","vendorName":"INCOME TAX INVESTIGATORS ASSOC","invoicePaymentDistAmount":50,"fundDesc":"General Fund","agencyDesc":"Pass Through Payments","agencyByAgencyCodeMasked":{"deptName":"Pass Through Payments","deptSlug":"pass-throughs","totalAmount":451128009.3},"appropDesc":"Undefined Appropriations","costcenterDesc":"Default Cost Center","objectDesc":"Empl W/H-Union Dues","objectDescShorthand":"Pass Through","vendorType":"ADVANCE PAY","partyType":"ORGANIZATION"},{"checkNumber":"3454091","checkDate":"2019-01-06T00:00:00","checkAmount":"20.00","statusCode":"CLEARED","vendorName":"INCOME TAX INVESTIGATORS ASSOC","invoicePaymentDistAmount":20,"fundDesc":"General Fund","agencyDesc":"Pass Through Payments","agencyByAgencyCodeMasked":{"deptName":"Pass Through Payments","deptSlug":"pass-throughs","totalAmount":451128009.3},"appropDesc":"Undefined Appropriations","costcenterDesc":"Default Cost Center","objectDesc":"Empl W/H-Other Deductions","objectDescShorthand":"Pass Through","vendorType":"ADVANCE PAY","partyType":"ORGANIZATION"},{"checkNumber":"3447387","checkDate":"2018-10-29T00:00:00","checkAmount":"20.00","statusCode":"CLEARED","vendorName":"INCOME TAX INVESTIGATORS ASSOC","invoicePaymentDistAmount":20,"fundDesc":"General Fund","agencyDesc":"Pass Through Payments","agencyByAgencyCodeMasked":{"deptName":"Pass Through Payments","deptSlug":"pass-throughs","totalAmount":451128009.3},"appropDesc":"Undefined Appropriations","costcenterDesc":"Default Cost Center","objectDesc":"Empl W/H-Other Deductions","objectDescShorthand":"Pass Through","vendorType":"ADVANCE PAY","partyType":"ORGANIZATION"},{"checkNumber":"2083501","checkDate":"2018-10-15T00:00:00","checkAmount":"20.00","statusCode":"CLEARED","vendorName":"INCOME TAX INVESTIGATORS ASSOC","invoicePaymentDistAmount":20,"fundDesc":"General Fund","agencyDesc":"Pass Through Payments","agencyByAgencyCodeMasked":{"deptName":"Pass Through Payments","deptSlug":"pass-throughs","totalAmount":451128009.3},"appropDesc":"Undefined Appropriations","costcenterDesc":"Default Cost Center","objectDesc":"Empl W/H-Other Deductions","objectDescShorthand":"Pass Through","vendorType":"ADVANCE PAY","partyType":"ORGANIZATION"},{"checkNumber":"3446192","checkDate":"2018-10-04T00:00:00","checkAmount":"20.00","statusCode":"CLEARED","vendorName":"INCOME TAX INVESTIGATORS ASSOC","invoicePaymentDistAmount":20,"fundDesc":"General Fund","agencyDesc":"Pass Through Payments","agencyByAgencyCodeMasked":{"deptName":"Pass Through Payments","deptSlug":"pass-throughs","totalAmount":451128009.3},"appropDesc":"Undefined Appropriations","costcenterDesc":"Default Cost Center","objectDesc":"Empl W/H-Other Deductions","objectDescShorthand":"Pass Through","vendorType":"ADVANCE PAY","partyType":"ORGANIZATION"},{"checkNumber":"3444873","checkDate":"2018-08-30T00:00:00","checkAmount":"20.00","statusCode":"CLEARED","vendorName":"INCOME TAX INVESTIGATORS ASSOC","invoicePaymentDistAmount":20,"fundDesc":"General Fund","agencyDesc":"Pass Through Payments","agencyByAgencyCodeMasked":{"deptName":"Pass Through Payments","deptSlug":"pass-throughs","totalAmount":451128009.3},"appropDesc":"Undefined Appropriations","costcenterDesc":"Default Cost Center","objectDesc":"Empl W/H-Other Deductions","objectDescShorthand":"Pass Through","vendorType":"ADVANCE PAY","partyType":"ORGANIZATION"},{"checkNumber":"2081096","checkDate":"2018-08-16T00:00:00","checkAmount":"20.00","statusCode":"NEGOTIABLE","vendorName":"INCOME TAX INVESTIGATORS ASSOC","invoicePaymentDistAmount":20,"fundDesc":"General Fund","agencyDesc":"Pass Through Payments","agencyByAgencyCodeMasked":{"deptName":"Pass Through Payments","deptSlug":"pass-throughs","totalAmount":451128009.3},"appropDesc":"Undefined Appropriations","costcenterDesc":"Default Cost Center","objectDesc":"Empl W/H-Other Deductions","objectDescShorthand":"Pass Through","vendorType":"ADVANCE PAY","partyType":"ORGANIZATION"},{"checkNumber":"2081073","checkDate":"2018-08-09T00:00:00","checkAmount":"20.00","statusCode":"CLEARED","vendorName":"INCOME TAX INVESTIGATORS ASSOC","invoicePaymentDistAmount":20,"fundDesc":"General Fund","agencyDesc":"Pass Through Payments","agencyByAgencyCodeMasked":{"deptName":"Pass Through Payments","deptSlug":"pass-throughs","totalAmount":451128009.3},"appropDesc":"Undefined Appropriations","costcenterDesc":"Default Cost Center","objectDesc":"Empl W/H-Other Deductions","objectDescShorthand":"Pass Through","vendorType":"ADVANCE PAY","partyType":"ORGANIZATION"},{"checkNumber":"3439988","checkDate":"2018-07-23T00:00:00","checkAmount":"20.00","statusCode":"CLEARED","vendorName":"INCOME TAX INVESTIGATORS ASSOC","invoicePaymentDistAmount":20,"fundDesc":"General Fund","agencyDesc":"Pass Through Payments","agencyByAgencyCodeMasked":{"deptName":"Pass Through Payments","deptSlug":"pass-throughs","totalAmount":451128009.3},"appropDesc":"Undefined Appropriations","costcenterDesc":"Default Cost Center","objectDesc":"Empl W/H-Other Deductions","objectDescShorthand":"Pass Through","vendorType":"ADVANCE PAY","partyType":"ORGANIZATION"},{"checkNumber":"2084115","checkDate":"2018-11-29T00:00:00","checkAmount":"50.00","statusCode":"CLEARED","vendorName":"INCOME TAX INVESTIGATORS ASSOC","invoicePaymentDistAmount":50,"fundDesc":"General Fund","agencyDesc":"Pass Through Payments","agencyByAgencyCodeMasked":{"deptName":"Pass Through Payments","deptSlug":"pass-throughs","totalAmount":451128009.3},"appropDesc":"Undefined Appropriations","costcenterDesc":"Default Cost Center","objectDesc":"Empl W/H-Union Dues","objectDescShorthand":"Pass Through","vendorType":"ADVANCE PAY","partyType":"ORGANIZATION"},{"checkNumber":"3439375","checkDate":"2018-07-12T00:00:00","checkAmount":"20.00","statusCode":"CLEARED","vendorName":"INCOME TAX INVESTIGATORS ASSOC","invoicePaymentDistAmount":20,"fundDesc":"General Fund","agencyDesc":"Pass Through Payments","agencyByAgencyCodeMasked":{"deptName":"Pass Through Payments","deptSlug":"pass-throughs","totalAmount":451128009.3},"appropDesc":"Undefined Appropriations","costcenterDesc":"Default Cost Center","objectDesc":"Empl W/H-Other Deductions","objectDescShorthand":"Pass Through","vendorType":"ADVANCE PAY","partyType":"ORGANIZATION"}]}]}},"pageContext":{"isCreatedByStatefulCreatePages":false,"number":"97749"}}