{"data":{"site":{"pathPrefix":"/open-checkbook"},"postgres":{"vendor":[{"vendorName":"FIREFIGHTERS ASSOCIATION","vendorAddress":"DETROIT, MI, 48226, US","vendorNumber":"97349","passThroughPayee":true,"payments":[{"checkNumber":"3462900","checkDate":"2019-06-27T00:00:00","checkAmount":"37513.89","statusCode":"CLEARED","vendorName":"FIREFIGHTERS ASSOCIATION","invoicePaymentDistAmount":37513.89,"fundDesc":"General Fund","agencyDesc":"Pass Through Payments","agencyByAgencyCodeMasked":{"deptName":"Pass Through Payments","deptSlug":"pass-throughs","totalAmount":451128009.3},"appropDesc":"Undefined Appropriations","costcenterDesc":"Default Cost Center","objectDesc":"Empl W/H-Other Deductions","objectDescShorthand":"Pass Through","vendorType":"NON-PO SUPPLIER","partyType":"ORGANIZATION"},{"checkNumber":"3462778","checkDate":"2019-06-20T00:00:00","checkAmount":"33.28","statusCode":"NEGOTIABLE","vendorName":"FIREFIGHTERS ASSOCIATION","invoicePaymentDistAmount":33.28,"fundDesc":"General Fund","agencyDesc":"Pass Through Payments","agencyByAgencyCodeMasked":{"deptName":"Pass Through Payments","deptSlug":"pass-throughs","totalAmount":451128009.3},"appropDesc":"Undefined Appropriations","costcenterDesc":"Default Cost Center","objectDesc":"Empl W/H-Other Deductions","objectDescShorthand":"Pass Through","vendorType":"NON-PO SUPPLIER","partyType":"ORGANIZATION"},{"checkNumber":"3462435","checkDate":"2019-06-13T00:00:00","checkAmount":"37826.08","statusCode":"CLEARED","vendorName":"FIREFIGHTERS ASSOCIATION","invoicePaymentDistAmount":37826.08,"fundDesc":"General Fund","agencyDesc":"Pass Through Payments","agencyByAgencyCodeMasked":{"deptName":"Pass Through Payments","deptSlug":"pass-throughs","totalAmount":451128009.3},"appropDesc":"Undefined Appropriations","costcenterDesc":"Default Cost Center","objectDesc":"Empl W/H-Other Deductions","objectDescShorthand":"Pass Through","vendorType":"NON-PO SUPPLIER","partyType":"ORGANIZATION"},{"checkNumber":"3462052","checkDate":"2019-06-06T00:00:00","checkAmount":"33.28","statusCode":"CLEARED","vendorName":"FIREFIGHTERS ASSOCIATION","invoicePaymentDistAmount":33.28,"fundDesc":"General Fund","agencyDesc":"Pass Through Payments","agencyByAgencyCodeMasked":{"deptName":"Pass Through Payments","deptSlug":"pass-throughs","totalAmount":451128009.3},"appropDesc":"Undefined Appropriations","costcenterDesc":"Default Cost Center","objectDesc":"Empl W/H-Other Deductions","objectDescShorthand":"Pass Through","vendorType":"NON-PO SUPPLIER","partyType":"ORGANIZATION"},{"checkNumber":"3461824","checkDate":"2019-05-30T00:00:00","checkAmount":"37619.96","statusCode":"CLEARED","vendorName":"FIREFIGHTERS ASSOCIATION","invoicePaymentDistAmount":37619.96,"fundDesc":"General Fund","agencyDesc":"Pass Through Payments","agencyByAgencyCodeMasked":{"deptName":"Pass Through Payments","deptSlug":"pass-throughs","totalAmount":451128009.3},"appropDesc":"Undefined Appropriations","costcenterDesc":"Default Cost Center","objectDesc":"Empl W/H-Other Deductions","objectDescShorthand":"Pass Through","vendorType":"NON-PO SUPPLIER","partyType":"ORGANIZATION"},{"checkNumber":"3461600","checkDate":"2019-05-23T00:00:00","checkAmount":"33.28","statusCode":"CLEARED","vendorName":"FIREFIGHTERS ASSOCIATION","invoicePaymentDistAmount":33.28,"fundDesc":"General Fund","agencyDesc":"Pass Through Payments","agencyByAgencyCodeMasked":{"deptName":"Pass Through Payments","deptSlug":"pass-throughs","totalAmount":451128009.3},"appropDesc":"Undefined Appropriations","costcenterDesc":"Default Cost Center","objectDesc":"Empl W/H-Other Deductions","objectDescShorthand":"Pass Through","vendorType":"NON-PO SUPPLIER","partyType":"ORGANIZATION"},{"checkNumber":"3460909","checkDate":"2019-05-16T00:00:00","checkAmount":"37751.12","statusCode":"CLEARED","vendorName":"FIREFIGHTERS ASSOCIATION","invoicePaymentDistAmount":37751.12,"fundDesc":"General Fund","agencyDesc":"Pass Through Payments","agencyByAgencyCodeMasked":{"deptName":"Pass Through Payments","deptSlug":"pass-throughs","totalAmount":451128009.3},"appropDesc":"Undefined Appropriations","costcenterDesc":"Default Cost Center","objectDesc":"Empl W/H-Other Deductions","objectDescShorthand":"Pass Through","vendorType":"NON-PO SUPPLIER","partyType":"ORGANIZATION"},{"checkNumber":"3460655","checkDate":"2019-05-14T00:00:00","checkAmount":"33.28","statusCode":"CLEARED","vendorName":"FIREFIGHTERS ASSOCIATION","invoicePaymentDistAmount":33.28,"fundDesc":"General Fund","agencyDesc":"Pass Through Payments","agencyByAgencyCodeMasked":{"deptName":"Pass Through Payments","deptSlug":"pass-throughs","totalAmount":451128009.3},"appropDesc":"Undefined Appropriations","costcenterDesc":"Default Cost Center","objectDesc":"Empl W/H-Other Deductions","objectDescShorthand":"Pass Through","vendorType":"NON-PO SUPPLIER","partyType":"ORGANIZATION"},{"checkNumber":"3460429","checkDate":"2019-05-02T00:00:00","checkAmount":"37821.96","statusCode":"CLEARED","vendorName":"FIREFIGHTERS ASSOCIATION","invoicePaymentDistAmount":37821.96,"fundDesc":"General Fund","agencyDesc":"Pass Through Payments","agencyByAgencyCodeMasked":{"deptName":"Pass Through Payments","deptSlug":"pass-throughs","totalAmount":451128009.3},"appropDesc":"Undefined Appropriations","costcenterDesc":"Default Cost Center","objectDesc":"Empl W/H-Other Deductions","objectDescShorthand":"Pass Through","vendorType":"NON-PO SUPPLIER","partyType":"ORGANIZATION"},{"checkNumber":"3460072","checkDate":"2019-04-25T00:00:00","checkAmount":"94.16","statusCode":"CLEARED","vendorName":"FIREFIGHTERS ASSOCIATION","invoicePaymentDistAmount":94.16,"fundDesc":"General Fund","agencyDesc":"Pass Through Payments","agencyByAgencyCodeMasked":{"deptName":"Pass Through Payments","deptSlug":"pass-throughs","totalAmount":451128009.3},"appropDesc":"Undefined Appropriations","costcenterDesc":"Default Cost Center","objectDesc":"Empl W/H-Other Deductions","objectDescShorthand":"Pass Through","vendorType":"NON-PO SUPPLIER","partyType":"ORGANIZATION"},{"checkNumber":"3459919","checkDate":"2019-04-17T00:00:00","checkAmount":"49201.80","statusCode":"CLEARED","vendorName":"FIREFIGHTERS ASSOCIATION","invoicePaymentDistAmount":49201.8,"fundDesc":"General Fund","agencyDesc":"Pass Through Payments","agencyByAgencyCodeMasked":{"deptName":"Pass Through Payments","deptSlug":"pass-throughs","totalAmount":451128009.3},"appropDesc":"Undefined Appropriations","costcenterDesc":"Default Cost Center","objectDesc":"Empl W/H-Other Deductions","objectDescShorthand":"Pass Through","vendorType":"NON-PO SUPPLIER","partyType":"ORGANIZATION"},{"checkNumber":"3459784","checkDate":"2019-04-11T00:00:00","checkAmount":"33.28","statusCode":"CLEARED","vendorName":"FIREFIGHTERS ASSOCIATION","invoicePaymentDistAmount":33.28,"fundDesc":"General Fund","agencyDesc":"Pass Through Payments","agencyByAgencyCodeMasked":{"deptName":"Pass Through Payments","deptSlug":"pass-throughs","totalAmount":451128009.3},"appropDesc":"Undefined Appropriations","costcenterDesc":"Default Cost Center","objectDesc":"Empl W/H-Other Deductions","objectDescShorthand":"Pass Through","vendorType":"NON-PO SUPPLIER","partyType":"ORGANIZATION"},{"checkNumber":"3459509","checkDate":"2019-04-04T00:00:00","checkAmount":"38021.64","statusCode":"CLEARED","vendorName":"FIREFIGHTERS ASSOCIATION","invoicePaymentDistAmount":38021.64,"fundDesc":"General Fund","agencyDesc":"Pass Through Payments","agencyByAgencyCodeMasked":{"deptName":"Pass Through Payments","deptSlug":"pass-throughs","totalAmount":451128009.3},"appropDesc":"Undefined Appropriations","costcenterDesc":"Default Cost Center","objectDesc":"Empl W/H-Other Deductions","objectDescShorthand":"Pass Through","vendorType":"NON-PO SUPPLIER","partyType":"ORGANIZATION"},{"checkNumber":"3459268","checkDate":"2019-03-29T00:00:00","checkAmount":"33.28","statusCode":"CLEARED","vendorName":"FIREFIGHTERS ASSOCIATION","invoicePaymentDistAmount":33.28,"fundDesc":"General Fund","agencyDesc":"Pass Through Payments","agencyByAgencyCodeMasked":{"deptName":"Pass Through Payments","deptSlug":"pass-throughs","totalAmount":451128009.3},"appropDesc":"Undefined Appropriations","costcenterDesc":"Default Cost Center","objectDesc":"Empl W/H-Other Deductions","objectDescShorthand":"Pass Through","vendorType":"NON-PO SUPPLIER","partyType":"ORGANIZATION"},{"checkNumber":"3458913","checkDate":"2019-03-24T00:00:00","checkAmount":"38144.76","statusCode":"NEGOTIABLE","vendorName":"FIREFIGHTERS ASSOCIATION","invoicePaymentDistAmount":38144.76,"fundDesc":"General Fund","agencyDesc":"Pass Through Payments","agencyByAgencyCodeMasked":{"deptName":"Pass Through Payments","deptSlug":"pass-throughs","totalAmount":451128009.3},"appropDesc":"Undefined Appropriations","costcenterDesc":"Default Cost Center","objectDesc":"Empl W/H-Other Deductions","objectDescShorthand":"Pass Through","vendorType":"NON-PO SUPPLIER","partyType":"ORGANIZATION"},{"checkNumber":"3458382","checkDate":"2019-03-07T00:00:00","checkAmount":"38496.66","statusCode":"CLEARED","vendorName":"FIREFIGHTERS ASSOCIATION","invoicePaymentDistAmount":38496.66,"fundDesc":"General Fund","agencyDesc":"Pass Through Payments","agencyByAgencyCodeMasked":{"deptName":"Pass Through Payments","deptSlug":"pass-throughs","totalAmount":451128009.3},"appropDesc":"Undefined Appropriations","costcenterDesc":"Default Cost Center","objectDesc":"Empl W/H-Other Deductions","objectDescShorthand":"Pass Through","vendorType":"NON-PO SUPPLIER","partyType":"ORGANIZATION"},{"checkNumber":"3457537","checkDate":"2019-02-22T00:00:00","checkAmount":"49723.22","statusCode":"CLEARED","vendorName":"FIREFIGHTERS ASSOCIATION","invoicePaymentDistAmount":49723.22,"fundDesc":"General Fund","agencyDesc":"Pass Through Payments","agencyByAgencyCodeMasked":{"deptName":"Pass Through Payments","deptSlug":"pass-throughs","totalAmount":451128009.3},"appropDesc":"Undefined Appropriations","costcenterDesc":"Default Cost Center","objectDesc":"Empl W/H-Other Deductions","objectDescShorthand":"Pass Through","vendorType":"NON-PO SUPPLIER","partyType":"ORGANIZATION"},{"checkNumber":"3456135","checkDate":"2019-02-12T00:00:00","checkAmount":"37379.73","statusCode":"CLEARED","vendorName":"FIREFIGHTERS ASSOCIATION","invoicePaymentDistAmount":37379.73,"fundDesc":"General Fund","agencyDesc":"Pass Through Payments","agencyByAgencyCodeMasked":{"deptName":"Pass Through Payments","deptSlug":"pass-throughs","totalAmount":451128009.3},"appropDesc":"Undefined Appropriations","costcenterDesc":"Default Cost Center","objectDesc":"Empl W/H-Other Deductions","objectDescShorthand":"Pass Through","vendorType":"NON-PO SUPPLIER","partyType":"ORGANIZATION"},{"checkNumber":"3455462","checkDate":"2019-01-31T00:00:00","checkAmount":"33.28","statusCode":"CLEARED","vendorName":"FIREFIGHTERS ASSOCIATION","invoicePaymentDistAmount":33.28,"fundDesc":"General Fund","agencyDesc":"Pass Through Payments","agencyByAgencyCodeMasked":{"deptName":"Pass Through Payments","deptSlug":"pass-throughs","totalAmount":451128009.3},"appropDesc":"Undefined Appropriations","costcenterDesc":"Default Cost Center","objectDesc":"Empl W/H-Other Deductions","objectDescShorthand":"Pass Through","vendorType":"NON-PO SUPPLIER","partyType":"ORGANIZATION"},{"checkNumber":"3455142","checkDate":"2019-01-24T00:00:00","checkAmount":"37675.97","statusCode":"CLEARED","vendorName":"FIREFIGHTERS ASSOCIATION","invoicePaymentDistAmount":37675.97,"fundDesc":"General Fund","agencyDesc":"Pass Through Payments","agencyByAgencyCodeMasked":{"deptName":"Pass Through Payments","deptSlug":"pass-throughs","totalAmount":451128009.3},"appropDesc":"Undefined Appropriations","costcenterDesc":"Default Cost Center","objectDesc":"Empl W/H-Other Deductions","objectDescShorthand":"Pass Through","vendorType":"NON-PO SUPPLIER","partyType":"ORGANIZATION"},{"checkNumber":"3454819","checkDate":"2019-01-17T00:00:00","checkAmount":"33.28","statusCode":"CLEARED","vendorName":"FIREFIGHTERS ASSOCIATION","invoicePaymentDistAmount":33.28,"fundDesc":"General Fund","agencyDesc":"Pass Through Payments","agencyByAgencyCodeMasked":{"deptName":"Pass Through Payments","deptSlug":"pass-throughs","totalAmount":451128009.3},"appropDesc":"Undefined Appropriations","costcenterDesc":"Default Cost Center","objectDesc":"Empl W/H-Other Deductions","objectDescShorthand":"Pass Through","vendorType":"NON-PO SUPPLIER","partyType":"ORGANIZATION"},{"checkNumber":"3454614","checkDate":"2019-01-10T00:00:00","checkAmount":"37440.00","statusCode":"NEGOTIABLE","vendorName":"FIREFIGHTERS ASSOCIATION","invoicePaymentDistAmount":37440,"fundDesc":"General Fund","agencyDesc":"Pass Through Payments","agencyByAgencyCodeMasked":{"deptName":"Pass Through Payments","deptSlug":"pass-throughs","totalAmount":451128009.3},"appropDesc":"Undefined Appropriations","costcenterDesc":"Default Cost Center","objectDesc":"Empl W/H-Other Deductions","objectDescShorthand":"Pass Through","vendorType":"NON-PO SUPPLIER","partyType":"ORGANIZATION"},{"checkNumber":"3454085","checkDate":"2019-01-06T00:00:00","checkAmount":"33.28","statusCode":"CLEARED","vendorName":"FIREFIGHTERS ASSOCIATION","invoicePaymentDistAmount":33.28,"fundDesc":"General Fund","agencyDesc":"Pass Through Payments","agencyByAgencyCodeMasked":{"deptName":"Pass Through Payments","deptSlug":"pass-throughs","totalAmount":451128009.3},"appropDesc":"Undefined Appropriations","costcenterDesc":"Default Cost Center","objectDesc":"Empl W/H-Other Deductions","objectDescShorthand":"Pass Through","vendorType":"NON-PO SUPPLIER","partyType":"ORGANIZATION"},{"checkNumber":"3453928","checkDate":"2019-01-03T00:00:00","checkAmount":"37812.37","statusCode":"CLEARED","vendorName":"FIREFIGHTERS ASSOCIATION","invoicePaymentDistAmount":37812.37,"fundDesc":"General Fund","agencyDesc":"Pass Through Payments","agencyByAgencyCodeMasked":{"deptName":"Pass Through Payments","deptSlug":"pass-throughs","totalAmount":451128009.3},"appropDesc":"Undefined Appropriations","costcenterDesc":"Default Cost Center","objectDesc":"Empl W/H-Other Deductions","objectDescShorthand":"Pass Through","vendorType":"NON-PO SUPPLIER","partyType":"ORGANIZATION"},{"checkNumber":"3453808","checkDate":"2018-12-20T00:00:00","checkAmount":"33.28","statusCode":"CLEARED","vendorName":"FIREFIGHTERS ASSOCIATION","invoicePaymentDistAmount":33.28,"fundDesc":"General Fund","agencyDesc":"Pass Through Payments","agencyByAgencyCodeMasked":{"deptName":"Pass Through Payments","deptSlug":"pass-throughs","totalAmount":451128009.3},"appropDesc":"Undefined Appropriations","costcenterDesc":"Default Cost Center","objectDesc":"Empl W/H-Other Deductions","objectDescShorthand":"Pass Through","vendorType":"NON-PO SUPPLIER","partyType":"ORGANIZATION"},{"checkNumber":"3453318","checkDate":"2018-12-14T00:00:00","checkAmount":"49112.37","statusCode":"CLEARED","vendorName":"FIREFIGHTERS ASSOCIATION","invoicePaymentDistAmount":49112.37,"fundDesc":"General Fund","agencyDesc":"Pass Through Payments","agencyByAgencyCodeMasked":{"deptName":"Pass Through Payments","deptSlug":"pass-throughs","totalAmount":451128009.3},"appropDesc":"Undefined Appropriations","costcenterDesc":"Default Cost Center","objectDesc":"Empl W/H-Other Deductions","objectDescShorthand":"Pass Through","vendorType":"NON-PO SUPPLIER","partyType":"ORGANIZATION"},{"checkNumber":"3452978","checkDate":"2018-12-06T00:00:00","checkAmount":"33.28","statusCode":"CLEARED","vendorName":"FIREFIGHTERS ASSOCIATION","invoicePaymentDistAmount":33.28,"fundDesc":"General Fund","agencyDesc":"Pass Through Payments","agencyByAgencyCodeMasked":{"deptName":"Pass Through Payments","deptSlug":"pass-throughs","totalAmount":451128009.3},"appropDesc":"Undefined Appropriations","costcenterDesc":"Default Cost Center","objectDesc":"Empl W/H-Other Deductions","objectDescShorthand":"Pass Through","vendorType":"NON-PO SUPPLIER","partyType":"ORGANIZATION"},{"checkNumber":"3452628","checkDate":"2018-11-29T00:00:00","checkAmount":"37780.13","statusCode":"CLEARED","vendorName":"FIREFIGHTERS ASSOCIATION","invoicePaymentDistAmount":37780.13,"fundDesc":"General Fund","agencyDesc":"Pass Through Payments","agencyByAgencyCodeMasked":{"deptName":"Pass Through Payments","deptSlug":"pass-throughs","totalAmount":451128009.3},"appropDesc":"Undefined Appropriations","costcenterDesc":"Default Cost Center","objectDesc":"Empl W/H-Other Deductions","objectDescShorthand":"Pass Through","vendorType":"NON-PO SUPPLIER","partyType":"ORGANIZATION"},{"checkNumber":"3452356","checkDate":"2018-11-26T00:00:00","checkAmount":"33.28","statusCode":"CLEARED","vendorName":"FIREFIGHTERS ASSOCIATION","invoicePaymentDistAmount":33.28,"fundDesc":"General Fund","agencyDesc":"Pass Through Payments","agencyByAgencyCodeMasked":{"deptName":"Pass Through Payments","deptSlug":"pass-throughs","totalAmount":451128009.3},"appropDesc":"Undefined Appropriations","costcenterDesc":"Default Cost Center","objectDesc":"Empl W/H-Other Deductions","objectDescShorthand":"Pass Through","vendorType":"NON-PO SUPPLIER","partyType":"ORGANIZATION"},{"checkNumber":"3452010","checkDate":"2018-11-19T00:00:00","checkAmount":"37979.81","statusCode":"CLEARED","vendorName":"FIREFIGHTERS ASSOCIATION","invoicePaymentDistAmount":37979.81,"fundDesc":"General Fund","agencyDesc":"Pass Through Payments","agencyByAgencyCodeMasked":{"deptName":"Pass Through Payments","deptSlug":"pass-throughs","totalAmount":451128009.3},"appropDesc":"Undefined Appropriations","costcenterDesc":"Default Cost Center","objectDesc":"Empl W/H-Other Deductions","objectDescShorthand":"Pass Through","vendorType":"NON-PO SUPPLIER","partyType":"ORGANIZATION"},{"checkNumber":"3448652","checkDate":"2018-11-20T00:00:00","checkAmount":"33.28","statusCode":"CLEARED","vendorName":"FIREFIGHTERS ASSOCIATION","invoicePaymentDistAmount":33.28,"fundDesc":"General Fund","agencyDesc":"Pass Through Payments","agencyByAgencyCodeMasked":{"deptName":"Pass Through Payments","deptSlug":"pass-throughs","totalAmount":451128009.3},"appropDesc":"Undefined Appropriations","costcenterDesc":"Default Cost Center","objectDesc":"Empl W/H-Other Deductions","objectDescShorthand":"Pass Through","vendorType":"NON-PO SUPPLIER","partyType":"ORGANIZATION"},{"checkNumber":"3447866","checkDate":"2018-11-04T00:00:00","checkAmount":"38410.39","statusCode":"CLEARED","vendorName":"FIREFIGHTERS ASSOCIATION","invoicePaymentDistAmount":38410.39,"fundDesc":"General Fund","agencyDesc":"Pass Through Payments","agencyByAgencyCodeMasked":{"deptName":"Pass Through Payments","deptSlug":"pass-throughs","totalAmount":451128009.3},"appropDesc":"Undefined Appropriations","costcenterDesc":"Default Cost Center","objectDesc":"Empl W/H-Other Deductions","objectDescShorthand":"Pass Through","vendorType":"NON-PO SUPPLIER","partyType":"ORGANIZATION"},{"checkNumber":"3447037","checkDate":"2018-10-22T00:00:00","checkAmount":"38627.11","statusCode":"CLEARED","vendorName":"FIREFIGHTERS ASSOCIATION","invoicePaymentDistAmount":38627.11,"fundDesc":"General Fund","agencyDesc":"Pass Through Payments","agencyByAgencyCodeMasked":{"deptName":"Pass Through Payments","deptSlug":"pass-throughs","totalAmount":451128009.3},"appropDesc":"Undefined Appropriations","costcenterDesc":"Default Cost Center","objectDesc":"Empl W/H-Other Deductions","objectDescShorthand":"Pass Through","vendorType":"NON-PO SUPPLIER","partyType":"ORGANIZATION"},{"checkNumber":"2083471","checkDate":"2018-10-15T00:00:00","checkAmount":"33.28","statusCode":"CLEARED","vendorName":"FIREFIGHTERS ASSOCIATION","invoicePaymentDistAmount":33.28,"fundDesc":"General Fund","agencyDesc":"Pass Through Payments","agencyByAgencyCodeMasked":{"deptName":"Pass Through Payments","deptSlug":"pass-throughs","totalAmount":451128009.3},"appropDesc":"Undefined Appropriations","costcenterDesc":"Default Cost Center","objectDesc":"Empl W/H-Other Deductions","objectDescShorthand":"Pass Through","vendorType":"NON-PO SUPPLIER","partyType":"ORGANIZATION"},{"checkNumber":"2083360","checkDate":"2018-10-07T00:00:00","checkAmount":"38377.11","statusCode":"CLEARED","vendorName":"FIREFIGHTERS ASSOCIATION","invoicePaymentDistAmount":38377.11,"fundDesc":"General Fund","agencyDesc":"Pass Through Payments","agencyByAgencyCodeMasked":{"deptName":"Pass Through Payments","deptSlug":"pass-throughs","totalAmount":451128009.3},"appropDesc":"Undefined Appropriations","costcenterDesc":"Default Cost Center","objectDesc":"Empl W/H-Other Deductions","objectDescShorthand":"Pass Through","vendorType":"NON-PO SUPPLIER","partyType":"ORGANIZATION"},{"checkNumber":"2082765","checkDate":"2018-09-24T00:00:00","checkAmount":"37573.12","statusCode":"CLEARED","vendorName":"FIREFIGHTERS ASSOCIATION","invoicePaymentDistAmount":37573.12,"fundDesc":"General Fund","agencyDesc":"Pass Through Payments","agencyByAgencyCodeMasked":{"deptName":"Pass Through Payments","deptSlug":"pass-throughs","totalAmount":451128009.3},"appropDesc":"Undefined Appropriations","costcenterDesc":"Default Cost Center","objectDesc":"Empl W/H-Other Deductions","objectDescShorthand":"Pass Through","vendorType":"NON-PO SUPPLIER","partyType":"ORGANIZATION"},{"checkNumber":"3445219","checkDate":"2018-09-13T00:00:00","checkAmount":"37939.20","statusCode":"CLEARED","vendorName":"FIREFIGHTERS ASSOCIATION","invoicePaymentDistAmount":37939.2,"fundDesc":"General Fund","agencyDesc":"Pass Through Payments","agencyByAgencyCodeMasked":{"deptName":"Pass Through Payments","deptSlug":"pass-throughs","totalAmount":451128009.3},"appropDesc":"Undefined Appropriations","costcenterDesc":"Default Cost Center","objectDesc":"Empl W/H-Other Deductions","objectDescShorthand":"Pass Through","vendorType":"NON-PO SUPPLIER","partyType":"ORGANIZATION"},{"checkNumber":"3444421","checkDate":"2018-08-23T00:00:00","checkAmount":"38259.87","statusCode":"CLEARED","vendorName":"FIREFIGHTERS ASSOCIATION","invoicePaymentDistAmount":38259.87,"fundDesc":"General Fund","agencyDesc":"Pass Through Payments","agencyByAgencyCodeMasked":{"deptName":"Pass Through Payments","deptSlug":"pass-throughs","totalAmount":451128009.3},"appropDesc":"Undefined Appropriations","costcenterDesc":"Default Cost Center","objectDesc":"Empl W/H-Other Deductions","objectDescShorthand":"Pass Through","vendorType":"NON-PO SUPPLIER","partyType":"ORGANIZATION"},{"checkNumber":"3441793","checkDate":"2018-08-09T00:00:00","checkAmount":"38375.44","statusCode":"CLEARED","vendorName":"FIREFIGHTERS ASSOCIATION","invoicePaymentDistAmount":38375.44,"fundDesc":"General Fund","agencyDesc":"Pass Through Payments","agencyByAgencyCodeMasked":{"deptName":"Pass Through Payments","deptSlug":"pass-throughs","totalAmount":451128009.3},"appropDesc":"Undefined Appropriations","costcenterDesc":"Default Cost Center","objectDesc":"Empl W/H-Other Deductions","objectDescShorthand":"Pass Through","vendorType":"NON-PO SUPPLIER","partyType":"ORGANIZATION"},{"checkNumber":"3440380","checkDate":"2018-07-30T00:00:00","checkAmount":"38042.80","statusCode":"CLEARED","vendorName":"FIREFIGHTERS ASSOCIATION","invoicePaymentDistAmount":38042.8,"fundDesc":"General Fund","agencyDesc":"Pass Through Payments","agencyByAgencyCodeMasked":{"deptName":"Pass Through Payments","deptSlug":"pass-throughs","totalAmount":451128009.3},"appropDesc":"Undefined Appropriations","costcenterDesc":"Default Cost Center","objectDesc":"Empl W/H-Other Deductions","objectDescShorthand":"Pass Through","vendorType":"NON-PO SUPPLIER","partyType":"ORGANIZATION"},{"checkNumber":"3439310","checkDate":"2018-07-12T00:00:00","checkAmount":"35038.23","statusCode":"CLEARED","vendorName":"FIREFIGHTERS ASSOCIATION","invoicePaymentDistAmount":35038.23,"fundDesc":"General Fund","agencyDesc":"Pass Through Payments","agencyByAgencyCodeMasked":{"deptName":"Pass Through Payments","deptSlug":"pass-throughs","totalAmount":451128009.3},"appropDesc":"Undefined Appropriations","costcenterDesc":"Default Cost Center","objectDesc":"Empl W/H-Other Deductions","objectDescShorthand":"Pass Through","vendorType":"NON-PO SUPPLIER","partyType":"ORGANIZATION"},{"checkNumber":"3438600","checkDate":"2018-07-01T00:00:00","checkAmount":"34860.91","statusCode":"CLEARED","vendorName":"FIREFIGHTERS ASSOCIATION","invoicePaymentDistAmount":34860.91,"fundDesc":"General Fund","agencyDesc":"Pass Through Payments","agencyByAgencyCodeMasked":{"deptName":"Pass Through Payments","deptSlug":"pass-throughs","totalAmount":451128009.3},"appropDesc":"Undefined Appropriations","costcenterDesc":"Default Cost Center","objectDesc":"Empl W/H-Other Deductions","objectDescShorthand":"Pass Through","vendorType":"NON-PO SUPPLIER","partyType":"ORGANIZATION"},{"checkNumber":"3458096","checkDate":"2019-02-28T00:00:00","checkAmount":"33.28","statusCode":"CLEARED","vendorName":"FIREFIGHTERS ASSOCIATION","invoicePaymentDistAmount":33.28,"fundDesc":"General Fund","agencyDesc":"Pass Through Payments","agencyByAgencyCodeMasked":{"deptName":"Pass Through Payments","deptSlug":"pass-throughs","totalAmount":451128009.3},"appropDesc":"Undefined Appropriations","costcenterDesc":"Default Cost Center","objectDesc":"Empl W/H-Other Deductions","objectDescShorthand":"Pass Through","vendorType":"NON-PO SUPPLIER","partyType":"ORGANIZATION"},{"checkNumber":"3458605","checkDate":"2019-03-14T00:00:00","checkAmount":"33.28","statusCode":"CLEARED","vendorName":"FIREFIGHTERS ASSOCIATION","invoicePaymentDistAmount":33.28,"fundDesc":"General Fund","agencyDesc":"Pass Through Payments","agencyByAgencyCodeMasked":{"deptName":"Pass Through Payments","deptSlug":"pass-throughs","totalAmount":451128009.3},"appropDesc":"Undefined Appropriations","costcenterDesc":"Default Cost Center","objectDesc":"Empl W/H-Other Deductions","objectDescShorthand":"Pass Through","vendorType":"NON-PO SUPPLIER","partyType":"ORGANIZATION"},{"checkNumber":"3456643","checkDate":"2019-02-15T00:00:00","checkAmount":"33.28","statusCode":"CLEARED","vendorName":"FIREFIGHTERS ASSOCIATION","invoicePaymentDistAmount":33.28,"fundDesc":"General Fund","agencyDesc":"Pass Through Payments","agencyByAgencyCodeMasked":{"deptName":"Pass Through Payments","deptSlug":"pass-throughs","totalAmount":451128009.3},"appropDesc":"Undefined Appropriations","costcenterDesc":"Default Cost Center","objectDesc":"Empl W/H-Other Deductions","objectDescShorthand":"Pass Through","vendorType":"NON-PO SUPPLIER","partyType":"ORGANIZATION"},{"checkNumber":"3447351","checkDate":"2018-10-25T00:00:00","checkAmount":"33.28","statusCode":"CLEARED","vendorName":"FIREFIGHTERS ASSOCIATION","invoicePaymentDistAmount":33.28,"fundDesc":"General Fund","agencyDesc":"Pass Through Payments","agencyByAgencyCodeMasked":{"deptName":"Pass Through Payments","deptSlug":"pass-throughs","totalAmount":451128009.3},"appropDesc":"Undefined Appropriations","costcenterDesc":"Default Cost Center","objectDesc":"Empl W/H-Other Deductions","objectDescShorthand":"Pass Through","vendorType":"NON-PO SUPPLIER","partyType":"ORGANIZATION"}]}]}},"pageContext":{"isCreatedByStatefulCreatePages":false,"number":"97349"}}