{"data":{"site":{"pathPrefix":"/open-checkbook"},"postgres":{"vendor":[{"vendorName":"SPRINT","vendorAddress":"PHOENIX, AZ, 85082, US","vendorNumber":"210075","passThroughPayee":false,"payments":[{"checkNumber":"3462253","checkDate":"2019-06-13T00:00:00","checkAmount":"892.00","statusCode":"CLEARED","vendorName":"SPRINT","invoicePaymentDistAmount":792,"fundDesc":"General Fund","agencyDesc":"Police Department","agencyByAgencyCodeMasked":{"deptName":"Police Department","deptSlug":"police","totalAmount":47125259.6400002},"appropDesc":"Police Support Services Bureau","costcenterDesc":"Resource Management Division","objectDesc":"Contract Svcs-Other-Misc","objectDescShorthand":"Professional and Contractual Services","vendorType":"PROPERTY TAX","partyType":"ORGANIZATION"},{"checkNumber":"3462253","checkDate":"2019-06-13T00:00:00","checkAmount":"892.00","statusCode":"CLEARED","vendorName":"SPRINT","invoicePaymentDistAmount":100,"fundDesc":"General Fund","agencyDesc":"Police Department","agencyByAgencyCodeMasked":{"deptName":"Police Department","deptSlug":"police","totalAmount":47125259.6400002},"appropDesc":"Police Support Services Bureau","costcenterDesc":"Resource Management Division","objectDesc":"Contract Svcs-Other-Misc","objectDescShorthand":"Professional and Contractual Services","vendorType":"PROPERTY TAX","partyType":"ORGANIZATION"}]}]}},"pageContext":{"isCreatedByStatefulCreatePages":false,"number":"210075"}}