{"data":{"site":{"pathPrefix":"/open-checkbook"},"postgres":{"vendor":[{"vendorName":"ABM INDUSTRIES INC dba ABM","vendorAddress":"Chicago, IL, 60674, US","vendorNumber":"301924","passThroughPayee":false,"payments":[{"checkNumber":"226683","checkDate":"2019-01-17T00:00:00","checkAmount":"1602.53","statusCode":"NEGOTIABLE","vendorName":"ABM INDUSTRIES INC dba ABM","invoicePaymentDistAmount":1602.53,"fundDesc":"Library","agencyDesc":"Detroit Public Library","agencyByAgencyCodeMasked":{"deptName":"Detroit Public Library","deptSlug":"detroit-public-library","totalAmount":8662912.67000001},"appropDesc":"Library Administrative Management","costcenterDesc":"DPL - Contract Maintenance","objectDesc":"Contract Scvs-Janitorial","objectDescShorthand":"Professional and Contractual Services","vendorType":"SUPPLIER","partyType":"ORGANIZATION"},{"checkNumber":"226516","checkDate":"2019-01-10T00:00:00","checkAmount":"17669.59","statusCode":"NEGOTIABLE","vendorName":"ABM INDUSTRIES INC dba ABM","invoicePaymentDistAmount":1736.04,"fundDesc":"Library","agencyDesc":"Detroit Public Library","agencyByAgencyCodeMasked":{"deptName":"Detroit Public Library","deptSlug":"detroit-public-library","totalAmount":8662912.67000001},"appropDesc":"Library Administrative Management","costcenterDesc":"DPL - Contract Maintenance","objectDesc":"Contract Scvs-Janitorial","objectDescShorthand":"Professional and Contractual Services","vendorType":"SUPPLIER","partyType":"ORGANIZATION"},{"checkNumber":"226516","checkDate":"2019-01-10T00:00:00","checkAmount":"17669.59","statusCode":"NEGOTIABLE","vendorName":"ABM INDUSTRIES INC dba ABM","invoicePaymentDistAmount":13432,"fundDesc":"Library","agencyDesc":"Detroit Public Library","agencyByAgencyCodeMasked":{"deptName":"Detroit Public Library","deptSlug":"detroit-public-library","totalAmount":8662912.67000001},"appropDesc":"Library Administrative Management","costcenterDesc":"DPL - Contract Maintenance","objectDesc":"Contract Scvs-Janitorial","objectDescShorthand":"Professional and Contractual Services","vendorType":"SUPPLIER","partyType":"ORGANIZATION"},{"checkNumber":"226516","checkDate":"2019-01-10T00:00:00","checkAmount":"17669.59","statusCode":"NEGOTIABLE","vendorName":"ABM INDUSTRIES INC dba ABM","invoicePaymentDistAmount":2501.55,"fundDesc":"Library","agencyDesc":"Detroit Public Library","agencyByAgencyCodeMasked":{"deptName":"Detroit Public Library","deptSlug":"detroit-public-library","totalAmount":8662912.67000001},"appropDesc":"Library Administrative Management","costcenterDesc":"DPL - Contract Maintenance","objectDesc":"Contract Scvs-Janitorial","objectDescShorthand":"Professional and Contractual Services","vendorType":"SUPPLIER","partyType":"ORGANIZATION"},{"checkNumber":"225982","checkDate":"2018-12-20T00:00:00","checkAmount":"45171.90","statusCode":"NEGOTIABLE","vendorName":"ABM INDUSTRIES INC dba ABM","invoicePaymentDistAmount":24988.44,"fundDesc":"Library","agencyDesc":"Detroit Public Library","agencyByAgencyCodeMasked":{"deptName":"Detroit Public Library","deptSlug":"detroit-public-library","totalAmount":8662912.67000001},"appropDesc":"Library Administrative Management","costcenterDesc":"DPL - Contract Maintenance","objectDesc":"Contract Scvs-Janitorial","objectDescShorthand":"Professional and Contractual Services","vendorType":"SUPPLIER","partyType":"ORGANIZATION"},{"checkNumber":"225982","checkDate":"2018-12-20T00:00:00","checkAmount":"45171.90","statusCode":"NEGOTIABLE","vendorName":"ABM INDUSTRIES INC dba ABM","invoicePaymentDistAmount":831,"fundDesc":"Library","agencyDesc":"Detroit Public Library","agencyByAgencyCodeMasked":{"deptName":"Detroit Public Library","deptSlug":"detroit-public-library","totalAmount":8662912.67000001},"appropDesc":"Library Administrative Management","costcenterDesc":"DPL - Contract Maintenance","objectDesc":"Contract Scvs-Janitorial","objectDescShorthand":"Professional and Contractual Services","vendorType":"SUPPLIER","partyType":"ORGANIZATION"},{"checkNumber":"225982","checkDate":"2018-12-20T00:00:00","checkAmount":"45171.90","statusCode":"NEGOTIABLE","vendorName":"ABM INDUSTRIES INC dba ABM","invoicePaymentDistAmount":17352.23,"fundDesc":"Library","agencyDesc":"Detroit Public Library","agencyByAgencyCodeMasked":{"deptName":"Detroit Public Library","deptSlug":"detroit-public-library","totalAmount":8662912.67000001},"appropDesc":"Library Administrative Management","costcenterDesc":"DPL - Contract Maintenance","objectDesc":"Contract Svcs-Other-Bldg Maint","objectDescShorthand":"Professional and Contractual Services","vendorType":"SUPPLIER","partyType":"ORGANIZATION"},{"checkNumber":"225982","checkDate":"2018-12-20T00:00:00","checkAmount":"45171.90","statusCode":"NEGOTIABLE","vendorName":"ABM INDUSTRIES INC dba ABM","invoicePaymentDistAmount":2000.23,"fundDesc":"Library","agencyDesc":"Detroit Public Library","agencyByAgencyCodeMasked":{"deptName":"Detroit Public Library","deptSlug":"detroit-public-library","totalAmount":8662912.67000001},"appropDesc":"Library Administrative Management","costcenterDesc":"DPL - Contract Maintenance","objectDesc":"Contract Scvs-Janitorial","objectDescShorthand":"Professional and Contractual Services","vendorType":"SUPPLIER","partyType":"ORGANIZATION"},{"checkNumber":"224354","checkDate":"2018-11-15T00:00:00","checkAmount":"60498.80","statusCode":"NEGOTIABLE","vendorName":"ABM INDUSTRIES INC dba ABM","invoicePaymentDistAmount":944.86,"fundDesc":"Library","agencyDesc":"Detroit Public Library","agencyByAgencyCodeMasked":{"deptName":"Detroit Public Library","deptSlug":"detroit-public-library","totalAmount":8662912.67000001},"appropDesc":"Library Administrative Management","costcenterDesc":"DPL - Contract Maintenance","objectDesc":"Contract Scvs-Janitorial","objectDescShorthand":"Professional and Contractual Services","vendorType":"SUPPLIER","partyType":"ORGANIZATION"},{"checkNumber":"224354","checkDate":"2018-11-15T00:00:00","checkAmount":"60498.80","statusCode":"NEGOTIABLE","vendorName":"ABM INDUSTRIES INC dba ABM","invoicePaymentDistAmount":34097.08,"fundDesc":"Library","agencyDesc":"Detroit Public Library","agencyByAgencyCodeMasked":{"deptName":"Detroit Public Library","deptSlug":"detroit-public-library","totalAmount":8662912.67000001},"appropDesc":"Library Administrative Management","costcenterDesc":"DPL - Contract Maintenance","objectDesc":"Contract Scvs-Janitorial","objectDescShorthand":"Professional and Contractual Services","vendorType":"SUPPLIER","partyType":"ORGANIZATION"},{"checkNumber":"224354","checkDate":"2018-11-15T00:00:00","checkAmount":"60498.80","statusCode":"NEGOTIABLE","vendorName":"ABM INDUSTRIES INC dba ABM","invoicePaymentDistAmount":23613.18,"fundDesc":"Library","agencyDesc":"Detroit Public Library","agencyByAgencyCodeMasked":{"deptName":"Detroit Public Library","deptSlug":"detroit-public-library","totalAmount":8662912.67000001},"appropDesc":"Library Administrative Management","costcenterDesc":"DPL - Contract Maintenance","objectDesc":"Contract Scvs-Janitorial","objectDescShorthand":"Professional and Contractual Services","vendorType":"SUPPLIER","partyType":"ORGANIZATION"},{"checkNumber":"223825","checkDate":"2018-11-01T00:00:00","checkAmount":"27542.92","statusCode":"CLEARED","vendorName":"ABM INDUSTRIES INC dba ABM","invoicePaymentDistAmount":23302.46,"fundDesc":"Library","agencyDesc":"Detroit Public Library","agencyByAgencyCodeMasked":{"deptName":"Detroit Public Library","deptSlug":"detroit-public-library","totalAmount":8662912.67000001},"appropDesc":"Library Administrative Management","costcenterDesc":"DPL - Contract Maintenance","objectDesc":"Contract Scvs-Janitorial","objectDescShorthand":"Professional and Contractual Services","vendorType":"SUPPLIER","partyType":"ORGANIZATION"},{"checkNumber":"223825","checkDate":"2018-11-01T00:00:00","checkAmount":"27542.92","statusCode":"CLEARED","vendorName":"ABM INDUSTRIES INC dba ABM","invoicePaymentDistAmount":714.5,"fundDesc":"Library","agencyDesc":"Detroit Public Library","agencyByAgencyCodeMasked":{"deptName":"Detroit Public Library","deptSlug":"detroit-public-library","totalAmount":8662912.67000001},"appropDesc":"Library Administrative Management","costcenterDesc":"DPL - Contract Maintenance","objectDesc":"Contract Scvs-Janitorial","objectDescShorthand":"Professional and Contractual Services","vendorType":"SUPPLIER","partyType":"ORGANIZATION"},{"checkNumber":"223825","checkDate":"2018-11-01T00:00:00","checkAmount":"27542.92","statusCode":"CLEARED","vendorName":"ABM INDUSTRIES INC dba ABM","invoicePaymentDistAmount":1844.53,"fundDesc":"Library","agencyDesc":"Detroit Public Library","agencyByAgencyCodeMasked":{"deptName":"Detroit Public Library","deptSlug":"detroit-public-library","totalAmount":8662912.67000001},"appropDesc":"Library Administrative Management","costcenterDesc":"DPL - Contract Maintenance","objectDesc":"Contract Scvs-Janitorial","objectDescShorthand":"Professional and Contractual Services","vendorType":"SUPPLIER","partyType":"ORGANIZATION"},{"checkNumber":"223825","checkDate":"2018-11-01T00:00:00","checkAmount":"27542.92","statusCode":"CLEARED","vendorName":"ABM INDUSTRIES INC dba ABM","invoicePaymentDistAmount":1681.43,"fundDesc":"Library","agencyDesc":"Detroit Public Library","agencyByAgencyCodeMasked":{"deptName":"Detroit Public Library","deptSlug":"detroit-public-library","totalAmount":8662912.67000001},"appropDesc":"Library Administrative Management","costcenterDesc":"DPL - Contract Maintenance","objectDesc":"Contract Scvs-Janitorial","objectDescShorthand":"Professional and Contractual Services","vendorType":"SUPPLIER","partyType":"ORGANIZATION"},{"checkNumber":"223500","checkDate":"2018-10-25T00:00:00","checkAmount":"34097.08","statusCode":"CLEARED","vendorName":"ABM INDUSTRIES INC dba ABM","invoicePaymentDistAmount":34097.08,"fundDesc":"Library","agencyDesc":"Detroit Public Library","agencyByAgencyCodeMasked":{"deptName":"Detroit Public Library","deptSlug":"detroit-public-library","totalAmount":8662912.67000001},"appropDesc":"Library Administrative Management","costcenterDesc":"DPL - Contract Maintenance","objectDesc":"Contract Scvs-Janitorial","objectDescShorthand":"Professional and Contractual Services","vendorType":"SUPPLIER","partyType":"ORGANIZATION"},{"checkNumber":"222635","checkDate":"2018-10-04T00:00:00","checkAmount":"127.16","statusCode":"CLEARED","vendorName":"ABM INDUSTRIES INC dba ABM","invoicePaymentDistAmount":127.16,"fundDesc":"Library","agencyDesc":"Detroit Public Library","agencyByAgencyCodeMasked":{"deptName":"Detroit Public Library","deptSlug":"detroit-public-library","totalAmount":8662912.67000001},"appropDesc":"Library Administrative Management","costcenterDesc":"DPL - Contract Maintenance","objectDesc":"Contract Scvs-Janitorial","objectDescShorthand":"Professional and Contractual Services","vendorType":"SUPPLIER","partyType":"ORGANIZATION"},{"checkNumber":"222506","checkDate":"2018-09-27T00:00:00","checkAmount":"1184.57","statusCode":"CLEARED","vendorName":"ABM INDUSTRIES INC dba ABM","invoicePaymentDistAmount":1184.57,"fundDesc":"Library","agencyDesc":"Detroit Public Library","agencyByAgencyCodeMasked":{"deptName":"Detroit Public Library","deptSlug":"detroit-public-library","totalAmount":8662912.67000001},"appropDesc":"Library Administrative Management","costcenterDesc":"DPL - Contract Maintenance","objectDesc":"Contract Scvs-Janitorial","objectDescShorthand":"Professional and Contractual Services","vendorType":"SUPPLIER","partyType":"ORGANIZATION"},{"checkNumber":"221408","checkDate":"2018-08-30T00:00:00","checkAmount":"88586.90","statusCode":"NEGOTIABLE","vendorName":"ABM INDUSTRIES INC dba ABM","invoicePaymentDistAmount":20392.74,"fundDesc":"Library","agencyDesc":"Detroit Public Library","agencyByAgencyCodeMasked":{"deptName":"Detroit Public Library","deptSlug":"detroit-public-library","totalAmount":8662912.67000001},"appropDesc":"Library Administrative Management","costcenterDesc":"DPL - Contract Maintenance","objectDesc":"Contract Scvs-Janitorial","objectDescShorthand":"Professional and Contractual Services","vendorType":"SUPPLIER","partyType":"ORGANIZATION"},{"checkNumber":"221408","checkDate":"2018-08-30T00:00:00","checkAmount":"88586.90","statusCode":"NEGOTIABLE","vendorName":"ABM INDUSTRIES INC dba ABM","invoicePaymentDistAmount":34097.08,"fundDesc":"Library","agencyDesc":"Detroit Public Library","agencyByAgencyCodeMasked":{"deptName":"Detroit Public Library","deptSlug":"detroit-public-library","totalAmount":8662912.67000001},"appropDesc":"Library Administrative Management","costcenterDesc":"DPL - Contract Maintenance","objectDesc":"Contract Scvs-Janitorial","objectDescShorthand":"Professional and Contractual Services","vendorType":"SUPPLIER","partyType":"ORGANIZATION"},{"checkNumber":"221408","checkDate":"2018-08-30T00:00:00","checkAmount":"88586.90","statusCode":"NEGOTIABLE","vendorName":"ABM INDUSTRIES INC dba ABM","invoicePaymentDistAmount":34097.08,"fundDesc":"Library","agencyDesc":"Detroit Public Library","agencyByAgencyCodeMasked":{"deptName":"Detroit Public Library","deptSlug":"detroit-public-library","totalAmount":8662912.67000001},"appropDesc":"Library Administrative Management","costcenterDesc":"DPL - Contract Maintenance","objectDesc":"Contract Scvs-Janitorial","objectDescShorthand":"Professional and Contractual Services","vendorType":"SUPPLIER","partyType":"ORGANIZATION"},{"checkNumber":"220856","checkDate":"2018-08-16T00:00:00","checkAmount":"117855.81","statusCode":"CLEARED","vendorName":"ABM INDUSTRIES INC dba ABM","invoicePaymentDistAmount":820.82,"fundDesc":"Library","agencyDesc":"Detroit Public Library","agencyByAgencyCodeMasked":{"deptName":"Detroit Public Library","deptSlug":"detroit-public-library","totalAmount":8662912.67000001},"appropDesc":"Library Administrative Management","costcenterDesc":"DPL - Contract Maintenance","objectDesc":"Contract Scvs-Janitorial","objectDescShorthand":"Professional and Contractual Services","vendorType":"SUPPLIER","partyType":"ORGANIZATION"},{"checkNumber":"220856","checkDate":"2018-08-16T00:00:00","checkAmount":"117855.81","statusCode":"CLEARED","vendorName":"ABM INDUSTRIES INC dba ABM","invoicePaymentDistAmount":24372.2,"fundDesc":"Library","agencyDesc":"Detroit Public Library","agencyByAgencyCodeMasked":{"deptName":"Detroit Public Library","deptSlug":"detroit-public-library","totalAmount":8662912.67000001},"appropDesc":"Library Administrative Management","costcenterDesc":"DPL - Contract Maintenance","objectDesc":"Contract Scvs-Janitorial","objectDescShorthand":"Professional and Contractual Services","vendorType":"SUPPLIER","partyType":"ORGANIZATION"},{"checkNumber":"220856","checkDate":"2018-08-16T00:00:00","checkAmount":"117855.81","statusCode":"CLEARED","vendorName":"ABM INDUSTRIES INC dba ABM","invoicePaymentDistAmount":1993.02,"fundDesc":"Library","agencyDesc":"Detroit Public Library","agencyByAgencyCodeMasked":{"deptName":"Detroit Public Library","deptSlug":"detroit-public-library","totalAmount":8662912.67000001},"appropDesc":"Library Administrative Management","costcenterDesc":"DPL - Contract Maintenance","objectDesc":"Contract Scvs-Janitorial","objectDescShorthand":"Professional and Contractual Services","vendorType":"SUPPLIER","partyType":"ORGANIZATION"},{"checkNumber":"220856","checkDate":"2018-08-16T00:00:00","checkAmount":"117855.81","statusCode":"CLEARED","vendorName":"ABM INDUSTRIES INC dba ABM","invoicePaymentDistAmount":34097.08,"fundDesc":"Library","agencyDesc":"Detroit Public Library","agencyByAgencyCodeMasked":{"deptName":"Detroit Public Library","deptSlug":"detroit-public-library","totalAmount":8662912.67000001},"appropDesc":"Library Administrative Management","costcenterDesc":"DPL - Contract Maintenance","objectDesc":"Contract Scvs-Janitorial","objectDescShorthand":"Professional and Contractual Services","vendorType":"SUPPLIER","partyType":"ORGANIZATION"},{"checkNumber":"220856","checkDate":"2018-08-16T00:00:00","checkAmount":"117855.81","statusCode":"CLEARED","vendorName":"ABM INDUSTRIES INC dba ABM","invoicePaymentDistAmount":22475.61,"fundDesc":"Library","agencyDesc":"Detroit Public Library","agencyByAgencyCodeMasked":{"deptName":"Detroit Public Library","deptSlug":"detroit-public-library","totalAmount":8662912.67000001},"appropDesc":"Library Administrative Management","costcenterDesc":"DPL - Contract Maintenance","objectDesc":"Contract Scvs-Janitorial","objectDescShorthand":"Professional and Contractual Services","vendorType":"SUPPLIER","partyType":"ORGANIZATION"},{"checkNumber":"220856","checkDate":"2018-08-16T00:00:00","checkAmount":"117855.81","statusCode":"CLEARED","vendorName":"ABM INDUSTRIES INC dba ABM","invoicePaymentDistAmount":34097.08,"fundDesc":"Library","agencyDesc":"Detroit Public Library","agencyByAgencyCodeMasked":{"deptName":"Detroit Public Library","deptSlug":"detroit-public-library","totalAmount":8662912.67000001},"appropDesc":"Library Administrative Management","costcenterDesc":"DPL - Contract Maintenance","objectDesc":"Contract Scvs-Janitorial","objectDescShorthand":"Professional and Contractual Services","vendorType":"SUPPLIER","partyType":"ORGANIZATION"},{"checkNumber":"220590","checkDate":"2018-08-09T00:00:00","checkAmount":"47.69","statusCode":"CLEARED","vendorName":"ABM INDUSTRIES INC dba ABM","invoicePaymentDistAmount":47.69,"fundDesc":"Library","agencyDesc":"Detroit Public Library","agencyByAgencyCodeMasked":{"deptName":"Detroit Public Library","deptSlug":"detroit-public-library","totalAmount":8662912.67000001},"appropDesc":"Library Administrative Management","costcenterDesc":"DPL - Facilities Maintenance","objectDesc":"Contract Scvs-Janitorial","objectDescShorthand":"Professional and Contractual Services","vendorType":"SUPPLIER","partyType":"ORGANIZATION"},{"checkNumber":"220213","checkDate":"2018-07-26T00:00:00","checkAmount":"36462.06","statusCode":"CLEARED","vendorName":"ABM INDUSTRIES INC dba ABM","invoicePaymentDistAmount":32584.9,"fundDesc":"Library","agencyDesc":"Detroit Public Library","agencyByAgencyCodeMasked":{"deptName":"Detroit Public Library","deptSlug":"detroit-public-library","totalAmount":8662912.67000001},"appropDesc":"Library Administrative Management","costcenterDesc":"DPL - Contract Maintenance","objectDesc":"Contract Scvs-Janitorial","objectDescShorthand":"Professional and Contractual Services","vendorType":"SUPPLIER","partyType":"ORGANIZATION"},{"checkNumber":"220213","checkDate":"2018-07-26T00:00:00","checkAmount":"36462.06","statusCode":"CLEARED","vendorName":"ABM INDUSTRIES INC dba ABM","invoicePaymentDistAmount":2023.84,"fundDesc":"Library","agencyDesc":"Detroit Public Library","agencyByAgencyCodeMasked":{"deptName":"Detroit Public Library","deptSlug":"detroit-public-library","totalAmount":8662912.67000001},"appropDesc":"Library Administrative Management","costcenterDesc":"DPL - Contract Maintenance","objectDesc":"Contract Scvs-Janitorial","objectDescShorthand":"Professional and Contractual Services","vendorType":"SUPPLIER","partyType":"ORGANIZATION"},{"checkNumber":"220213","checkDate":"2018-07-26T00:00:00","checkAmount":"36462.06","statusCode":"CLEARED","vendorName":"ABM INDUSTRIES INC dba ABM","invoicePaymentDistAmount":1662.58,"fundDesc":"Library","agencyDesc":"Detroit Public Library","agencyByAgencyCodeMasked":{"deptName":"Detroit Public Library","deptSlug":"detroit-public-library","totalAmount":8662912.67000001},"appropDesc":"Library Administrative Management","costcenterDesc":"DPL - Contract Maintenance","objectDesc":"Contract Scvs-Janitorial","objectDescShorthand":"Professional and Contractual Services","vendorType":"SUPPLIER","partyType":"ORGANIZATION"},{"checkNumber":"220213","checkDate":"2018-07-26T00:00:00","checkAmount":"36462.06","statusCode":"CLEARED","vendorName":"ABM INDUSTRIES INC dba ABM","invoicePaymentDistAmount":190.74,"fundDesc":"Library","agencyDesc":"Detroit Public Library","agencyByAgencyCodeMasked":{"deptName":"Detroit Public Library","deptSlug":"detroit-public-library","totalAmount":8662912.67000001},"appropDesc":"Library Administrative Management","costcenterDesc":"DPL - Contract Maintenance","objectDesc":"Contract Scvs-Janitorial","objectDescShorthand":"Professional and Contractual Services","vendorType":"SUPPLIER","partyType":"ORGANIZATION"},{"checkNumber":"219617","checkDate":"2018-07-12T00:00:00","checkAmount":"2784.26","statusCode":"CLEARED","vendorName":"ABM INDUSTRIES INC dba ABM","invoicePaymentDistAmount":190.74,"fundDesc":"Library","agencyDesc":"Detroit Public Library","agencyByAgencyCodeMasked":{"deptName":"Detroit Public Library","deptSlug":"detroit-public-library","totalAmount":8662912.67000001},"appropDesc":"Library Administrative Management","costcenterDesc":"DPL - Contract Maintenance","objectDesc":"Contract Scvs-Janitorial","objectDescShorthand":"Professional and Contractual Services","vendorType":"SUPPLIER","partyType":"ORGANIZATION"},{"checkNumber":"219617","checkDate":"2018-07-12T00:00:00","checkAmount":"2784.26","statusCode":"CLEARED","vendorName":"ABM INDUSTRIES INC dba ABM","invoicePaymentDistAmount":2459.59,"fundDesc":"Library","agencyDesc":"Detroit Public Library","agencyByAgencyCodeMasked":{"deptName":"Detroit Public Library","deptSlug":"detroit-public-library","totalAmount":8662912.67000001},"appropDesc":"Library Administrative Management","costcenterDesc":"DPL - Contract Maintenance","objectDesc":"Contract Scvs-Janitorial","objectDescShorthand":"Professional and Contractual Services","vendorType":"SUPPLIER","partyType":"ORGANIZATION"},{"checkNumber":"219617","checkDate":"2018-07-12T00:00:00","checkAmount":"2784.26","statusCode":"CLEARED","vendorName":"ABM INDUSTRIES INC dba ABM","invoicePaymentDistAmount":70.35,"fundDesc":"Library","agencyDesc":"Detroit Public Library","agencyByAgencyCodeMasked":{"deptName":"Detroit Public Library","deptSlug":"detroit-public-library","totalAmount":8662912.67000001},"appropDesc":"Library Administrative Management","costcenterDesc":"DPL - Contract Maintenance","objectDesc":"Contract Scvs-Janitorial","objectDescShorthand":"Professional and Contractual Services","vendorType":"SUPPLIER","partyType":"ORGANIZATION"},{"checkNumber":"219617","checkDate":"2018-07-12T00:00:00","checkAmount":"2784.26","statusCode":"CLEARED","vendorName":"ABM INDUSTRIES INC dba ABM","invoicePaymentDistAmount":31.79,"fundDesc":"Library","agencyDesc":"Detroit Public Library","agencyByAgencyCodeMasked":{"deptName":"Detroit Public Library","deptSlug":"detroit-public-library","totalAmount":8662912.67000001},"appropDesc":"Library Administrative Management","costcenterDesc":"DPL - Contract Maintenance","objectDesc":"Contract Scvs-Janitorial","objectDescShorthand":"Professional and Contractual Services","vendorType":"SUPPLIER","partyType":"ORGANIZATION"},{"checkNumber":"219617","checkDate":"2018-07-12T00:00:00","checkAmount":"2784.26","statusCode":"CLEARED","vendorName":"ABM INDUSTRIES INC dba ABM","invoicePaymentDistAmount":31.79,"fundDesc":"Library","agencyDesc":"Detroit Public Library","agencyByAgencyCodeMasked":{"deptName":"Detroit Public Library","deptSlug":"detroit-public-library","totalAmount":8662912.67000001},"appropDesc":"Library Administrative Management","costcenterDesc":"DPL - Contract Maintenance","objectDesc":"Contract Scvs-Janitorial","objectDescShorthand":"Professional and Contractual Services","vendorType":"SUPPLIER","partyType":"ORGANIZATION"},{"checkNumber":"224354","checkDate":"2018-11-15T00:00:00","checkAmount":"60498.80","statusCode":"NEGOTIABLE","vendorName":"ABM INDUSTRIES INC dba ABM","invoicePaymentDistAmount":1843.68,"fundDesc":"Library","agencyDesc":"Detroit Public Library","agencyByAgencyCodeMasked":{"deptName":"Detroit Public Library","deptSlug":"detroit-public-library","totalAmount":8662912.67000001},"appropDesc":"Library Administrative Management","costcenterDesc":"DPL - Contract Maintenance","objectDesc":"Contract Scvs-Janitorial","objectDescShorthand":"Professional and Contractual Services","vendorType":"SUPPLIER","partyType":"ORGANIZATION"}]}]}},"pageContext":{"isCreatedByStatefulCreatePages":false,"number":"301924"}}